fastcubicspline/__init__.py
fastcubicspline/fcs.py
fastcubicspline/fcs_c.c
fastcubicspline/fcs_c.cpython-311-x86_64-linux-gnu.so
fastcubicspline/fcs_c.pyx
fastcubicspline-1.1.5.dist-info/METADATA
fastcubicspline-1.1.5.dist-info/WHEEL
fastcubicspline-1.1.5.dist-info/RECORD
