Metadata-Version: 2.1
Name: fastcubicspline
Version: 1.1.5
Summary: A fast cubic spline interpolator for real and complex data.
Home-page: https://github.com/cimatosa/fcSpline
License: BSD (3 clause)
Author: Richard Hartmann
Author-email: richard.hartmann@tu-dresden.de
Requires-Python: >=3.9,<4.0
Classifier: Intended Audience :: Science/Research
Classifier: License :: OSI Approved :: BSD License
Classifier: License :: Other/Proprietary License
Classifier: Operating System :: OS Independent
Classifier: Programming Language :: Python :: 3
Classifier: Programming Language :: Python :: 3.9
Classifier: Programming Language :: Python :: 3.10
Classifier: Programming Language :: Python :: 3.11
Classifier: Topic :: Utilities
Requires-Dist: black (>=23.7.0,<24.0.0)
Requires-Dist: matplotlib (>=3.7.2,<4.0.0)
Requires-Dist: numpy (>=1.20.3,<2.0.0)
Project-URL: Repository, https://github.com/cimatosa/fcSpline
